client/__init__.py
client/client.py
client/worker.py
ign_gpao_client-0.18.0.dist-info/METADATA
ign_gpao_client-0.18.0.dist-info/WHEEL
ign_gpao_client-0.18.0.dist-info/top_level.txt
ign_gpao_client-0.18.0.dist-info/RECORD
