Metadata-Version: 2.1
Name: ign-gpao-client
Version: 0.18.0
Summary: Client GPAO
Home-page: https://github.com/ign-gpao/client.git
Author: IGN
Author-email: arnaud.birk@ign.fr
License: MIT
Platform: UNKNOWN
Classifier: License :: OSI Approved :: MIT License
Classifier: Programming Language :: Python :: 3
Classifier: Programming Language :: Python :: 3.8
